jaraco/docker/__init__.py
jaraco/docker/check-issue7295.py
jaraco/docker/py.typed
jaraco.docker-2.3.0.dist-info/LICENSE
jaraco.docker-2.3.0.dist-info/METADATA
jaraco.docker-2.3.0.dist-info/WHEEL
jaraco.docker-2.3.0.dist-info/top_level.txt
jaraco.docker-2.3.0.dist-info/RECORD
